lscealice/ALICE.py
lscealice/__init__.py
lscealice/dialogs/__init__.py
lscealice/dialogs/newtiepoint.py
lscealice/dialogtools.py
lscealice/dic.py
lscealice/draw/__init__.py
lscealice/draw/artist.py
lscealice/draw/limits.py
lscealice/excel.py
lscealice/export.py
lscealice/figures.py
lscealice/icon/lapin.png
lscealice/load.py
lscealice/magic.py
lscealice/plt.py
lscealice/system.py
lscealice/utils.py
lscealice-0.1.10.dist-info/LICENSE
lscealice-0.1.10.dist-info/METADATA
lscealice-0.1.10.dist-info/WHEEL
lscealice-0.1.10.dist-info/entry_points.txt
lscealice-0.1.10.dist-info/RECORD
